LICENSE
README.md
setup.py
src/etc/config_example.ini
src/etc/logconf.ini
src/etc/scheduler_example.ini
src/teachable/__init__.py
src/teachable/api.py
src/teachable/course.py
src/teachable/school.py
src/teachable/user.py
src/teachable/scripts/__init__.py
src/teachable/scripts/auto_unenroll.py
src/teachable/scripts/change_password.py
src/teachable/scripts/enroll.py
src/teachable/scripts/leaderboard.py
src/teachable/scripts/list_courses.py
src/teachable/scripts/remind.py
src/teachable/scripts/scheduler.py
src/teachable/scripts/search_users.py
src/teachable/scripts/statements.py
src/teachable/scripts/teachable.py
src/teachable/scripts/unenroll.py
src/teachable/scripts/user_report.py
src/teachable/utils/__init__.py
src/teachable/utils/common.py
src/teachable/utils/email_utils.py
src/teachable_school_manager.egg-info/PKG-INFO
src/teachable_school_manager.egg-info/SOURCES.txt
src/teachable_school_manager.egg-info/dependency_links.txt
src/teachable_school_manager.egg-info/entry_points.txt
src/teachable_school_manager.egg-info/requires.txt
src/teachable_school_manager.egg-info/top_level.txt
templates/auto_unenroll.txt
templates/change_password.txt
templates/email_inactive.txt
templates/email_notstarted.txt
templates/unenroll.txt
templates/weekly_report.html