Metadata-Version: 2.1
Name: teachable-school-manager
Version: 2.2
Summary: Manage your Teachable school using the unofficial Teachable API
Home-page: https://github.com/stezz/teachable-scripts
Author: Stefano Mosconi
Author-email: stefano.mosconi@gmail.com
License: UNKNOWN
Project-URL: Bug Reports, https://github.com/stezz/teachable-scripts/issues
Project-URL: Source, https://github.com/stezz/teachable-scripts/
Keywords: scripts teachable
Platform: UNKNOWN
Classifier: Development Status :: 4 - Beta
Classifier: Intended Audience :: Developers
Classifier: Topic :: Education
Classifier: License :: OSI Approved :: MIT License
Classifier: Programming Language :: Python :: 3
Requires-Python: >3.7, <4
Provides-Extra: dev
License-File: LICENSE
